test.py
number_sequence/__init__.py
number_sequence/number_sequence.py
number_sequence-0.0.1.dist-info/LICENSE
number_sequence-0.0.1.dist-info/METADATA
number_sequence-0.0.1.dist-info/WHEEL
number_sequence-0.0.1.dist-info/top_level.txt
number_sequence-0.0.1.dist-info/RECORD
