Metadata-Version: 2.1
Name: number-sequence
Version: 0.0.1
Summary: Package to generate commonly used number sequences
Author-email: Ashish Mukherjee <ashishmukherjee@protonmail.com>
Project-URL: Homepage, https://github.com/ashish-m-yh/math/tree/main/number_sequence
Project-URL: Bug Tracker, https://github.com/ashish-m-yh/math/issues
Classifier: Programming Language :: Python :: 3
Classifier: License :: OSI Approved :: MIT License
Classifier: Operating System :: OS Independent
Requires-Python: >=3.7
License-File: LICENSE
